README.rst
setup.py
xutils/__init__.py
xutils/atexit.py
xutils/circuit_breaker.py
xutils/config.py
xutils/const.py
xutils/lifemanager.py
xutils/lock.py
xutils/log.py
xutils/mail.py
xutils/messager.py
xutils/net.py
xutils/pool.py
xutils/process.py
xutils/rate.py
xutils/retry.py
xutils/sqlalchemy.py
xutils/util.py
xutils/version.py
xutils/waitgroup.py
xutils/wsgi.py
xutils/xml2json.py
xutils.egg-info/PKG-INFO
xutils.egg-info/SOURCES.txt
xutils.egg-info/dependency_links.txt
xutils.egg-info/top_level.txt
xutils/gunicorn_workers/__init__.py
xutils/gunicorn_workers/geventlettask.py