Metadata-Version: 1.1
Name: xutils
Version: 2.2.2
Summary: A Fragmentary Python Library, no any third-part dependencies.
Home-page: https://github.com/xgfone/xutils
Author: xgfone
Author-email: xgfone@126.com
License: UNKNOWN
Platform: UNKNOWN
Classifier: License :: OSI Approved :: MIT License
Classifier: Programming Language :: Python
Classifier: Programming Language :: Python :: 2
Classifier: Programming Language :: Python :: 2.7
Classifier: Programming Language :: Python :: 3
Classifier: Programming Language :: Python :: 3.3
Classifier: Programming Language :: Python :: 3.4
Classifier: Programming Language :: Python :: 3.5
Classifier: Programming Language :: Python :: 3.6
Classifier: Programming Language :: Python :: 3.7
